{"stats":{"minecraft:used":{"minecraft:white_wool":2,"minecraft:soul_campfire":3,"minecraft:stone":5,"minecraft:lantern":133},"minecraft:picked_up":{"minecraft:lantern":1},"minecraft:custom":{"minecraft:jump":550,"minecraft:time_since_rest":59237,"minecraft:damage_taken":280,"minecraft:crouch_one_cm":8759,"minecraft:leave_game":4,"minecraft:play_time":59632,"minecraft:sprint_one_cm":76485,"minecraft:time_since_death":59190,"minecraft:walk_one_cm":34262,"minecraft:deaths":1,"minecraft:sneak_time":2512,"minecraft:total_world_time":59632,"minecraft:fly_one_cm":472291}},"DataVersion":3700}